[
  {
    "ml_folder": "ml-00_baseline",
    "experiment_id": "ml_00_test",
    "run_id": "run_02_xgb_native_cat_15f",
    "model_run_id": "default_00",
    "status": "representative_final",
    "selected_at": "2026-05-21",
    "description": "ML 베이스라인",
    "note": "ML-00, 파이프라인구축 및 코드 실행 준비용 기본 실험"
  },
  {
    "ml_folder": "ml-01",
    "experiment_id": "ml_01",
    "run_id": "r02",
    "model_run_id": "d00-fixparam-format-out",
    "status": "candidate_val_only",
    "selected_at": "2026-05-29",
    "description": "일반 집계 피처 1단계",
    "note": "ML-01, 파라미터 고정, 고카디널리티 컬럼(bank code, bank pair code),payment_format 을 제외한 정책으로 학습"
  },
  {
    "ml_folder": "ml-02",
    "experiment_id": "ml_02",
    "run_id": "r02",
    "model_run_id": "d00-optuna-in-format-rev2-t50",
    "status": "test_final",
    "selected_at": "2026-06-09",
    "description": "일반 집계 피처 2단계",
    "note": "ML-02, ML-01과 동일 정책, optuna 하이퍼 파라미터 튜닝 적용"
  },
  {
    "ml_folder": "ml-03",
    "experiment_id": "ml_03",
    "run_id": "r00",
    "model_run_id": "d00-fixparam",
    "status": "candidate_val_only",
    "selected_at": "2026-05-28",
    "description": "그래프 피처 1단계 - Fan-in/Fan-out",
    "note": "ML-03, ML-02와 동일 정책, 고정 파라미터 적용"
  },
  {
  "ml_folder": "ml-04",
  "experiment_id": "ml_04",
  "run_id": "r01",
  "model_run_id": "d00-fixparam",
  "status": "candidate_val_only",
  "selected_at": "2026-05-28",
  "description": "그래프 피처 2단계 - sender-receiver pair",
  "note": "ML-04, ML-03 피처 + sender-receiver pair 피처 추가, pair raw ratio 3개는 ML 입력에서 제외, 고정 파라미터 적용"
 },
{
  "ml_folder": "ml-05",
  "experiment_id": "ml_05",
  "run_id": "r00",
  "model_run_id": "d00-optuna_t25",
  "status": "candidate_val_only",
  "selected_at": "2026-05-29",
  "description": "그래프 피처 3단계 - flow-balance, pass-through",
  "note": "ML-05, ML-04 피처 + flow-balance/pass-through 피처 48개 추가, pair raw ratio 3개 입력 제외, Optuna 25 trial 튜닝 적용."
},
{
"ml_folder": "ml-06",
"experiment_id": "ml_06",
"run_id": "r00",
"model_run_id": "d00-optuna-t25-clip_p9999",
"status": "candidate_val_only",
"selected_at": "2026-06-01",
"description": "ML-06 ratio 안정화 full reference",
"note": "ML-06, ML-05 236-feature 계열에서 ratio 계열 21개를 train 기준 p99.99 clip variant로 안정화, Optuna 25 trial 튜닝"
},
{
"ml_folder": "ml-07",
"experiment_id": "ml_07",
"run_id": "r00",
"model_run_id": "ml07-d00-md4-top12-plus-fanin-formatoptuna-f1-t25",
"status": "test_final",
"selected_at": "2026-06-08",
"description": "ML-07 피쳐 다이어트 후보군 실험",
"note": "ML-07, 피쳐 다이어트 후보군 실험"
}
]